aliyunsdkdevops_rdc/__init__.py
aliyunsdkdevops_rdc/request/__init__.py
aliyunsdkdevops_rdc/request/v20200303/AddCodeupSourceToPipelineRequest.py
aliyunsdkdevops_rdc/request/v20200303/BatchInsertMembersRequest.py
aliyunsdkdevops_rdc/request/v20200303/CancelPipelineRequest.py
aliyunsdkdevops_rdc/request/v20200303/CheckAliyunAccountExistsRequest.py
aliyunsdkdevops_rdc/request/v20200303/CreateCommonGroupRequest.py
aliyunsdkdevops_rdc/request/v20200303/CreateCredentialRequest.py
aliyunsdkdevops_rdc/request/v20200303/CreateDevopsOrganizationRequest.py
aliyunsdkdevops_rdc/request/v20200303/CreateDevopsProjectRequest.py
aliyunsdkdevops_rdc/request/v20200303/CreateDevopsProjectSprintRequest.py
aliyunsdkdevops_rdc/request/v20200303/CreateDevopsProjectTaskRequest.py
aliyunsdkdevops_rdc/request/v20200303/CreatePipelineFromTemplateRequest.py
aliyunsdkdevops_rdc/request/v20200303/CreatePipelineRequest.py
aliyunsdkdevops_rdc/request/v20200303/CreateServiceConnectionRequest.py
aliyunsdkdevops_rdc/request/v20200303/DeleteCommonGroupRequest.py
aliyunsdkdevops_rdc/request/v20200303/DeleteDevopsOrganizationMembersRequest.py
aliyunsdkdevops_rdc/request/v20200303/DeleteDevopsOrganizationRequest.py
aliyunsdkdevops_rdc/request/v20200303/DeleteDevopsProjectMembersRequest.py
aliyunsdkdevops_rdc/request/v20200303/DeleteDevopsProjectRequest.py
aliyunsdkdevops_rdc/request/v20200303/DeleteDevopsProjectSprintRequest.py
aliyunsdkdevops_rdc/request/v20200303/DeleteDevopsProjectTaskRequest.py
aliyunsdkdevops_rdc/request/v20200303/DeletePipelineMemberRequest.py
aliyunsdkdevops_rdc/request/v20200303/ExecutePipelineRequest.py
aliyunsdkdevops_rdc/request/v20200303/GetDevopsOrganizationMembersRequest.py
aliyunsdkdevops_rdc/request/v20200303/GetDevopsProjectInfoRequest.py
aliyunsdkdevops_rdc/request/v20200303/GetDevopsProjectMembersRequest.py
aliyunsdkdevops_rdc/request/v20200303/GetDevopsProjectSprintInfoRequest.py
aliyunsdkdevops_rdc/request/v20200303/GetDevopsProjectTaskInfoRequest.py
aliyun_python_sdk_devops_rdc-2.0.2.dist-info/LICENSE
aliyun_python_sdk_devops_rdc-2.0.2.dist-info/METADATA
aliyun_python_sdk_devops_rdc-2.0.2.dist-info/WHEEL
aliyun_python_sdk_devops_rdc-2.0.2.dist-info/top_level.txt
aliyun_python_sdk_devops_rdc-2.0.2.dist-info/RECORD
